{
  "stats": {
    "totalProducts": 43149,
    "productsWithCategory": 43149,
    "productsWithoutCategory": 0,
    "productsWithSubcategory": 0,
    "productsWithoutSubcategory": 43149,
    "productsWithMultipleSubcategories": 0,
    "productsByCategory": {
      "68b2f7a465a5cb13315a52bb": 4525,
      "68b2f79d65a5cb13315a529a": 9394,
      "68b2f7a065a5cb13315a52a7": 1904,
      "68b2f7a165a5cb13315a52ae": 4423,
      "68b2f79f65a5cb13315a52a5": 22903
    },
    "productsBySubcategory": {},
    "categoriesFound": [
      "68b2f7a465a5cb13315a52bb",
      "68b2f79d65a5cb13315a529a",
      "68b2f7a065a5cb13315a52a7",
      "68b2f7a165a5cb13315a52ae",
      "68b2f79f65a5cb13315a52a5"
    ],
    "subcategoriesFound": [],
    "issues": []
  },
  "productsWithoutSubcategory": [
    {
      "productId": "68be85ad094d08828def453a",
      "productName": "Shoppingvagn",
      "categoryId": "68b2f7a465a5cb13315a52bb"
    },
    {
      "productId": "68be85ad094d08828def453b",
      "productName": "Resväska 75 cm, 4 hjul, Lyxig inredning, Expanderbar",
      "categoryId": "68b2f79d65a5cb13315a529a"
    },
    {
      "productId": "68be85ad094d08828def453c",
      "productName": "Resväska 55 cm, 4 hjul, lyxig inredning, expanderbar",
      "categoryId": "68b2f7a465a5cb13315a52bb"
    },
    {
      "productId": "68be85ad094d08828def453d",
      "productName": "Set med resväskor, S/M/L",
      "categoryId": "68b2f79d65a5cb13315a529a"
    },
    {
      "productId": "68be85ad094d08828def453e",
      "productName": "Swift S",
      "categoryId": "68b2f7a465a5cb13315a52bb"
    },
    {
      "productId": "68be85ad094d08828def453f",
      "productName": "Set Med Resväskor, S/M/L",
      "categoryId": "68b2f7a465a5cb13315a52bb"
    },
    {
      "productId": "68be85ad094d08828def4540",
      "productName": "Swift L",
      "categoryId": "68b2f7a465a5cb13315a52bb"
    },
    {
      "productId": "68be85ad094d08828def4541",
      "productName": "Swift M",
      "categoryId": "68b2f7a465a5cb13315a52bb"
    },
    {
      "productId": "68be85ad094d08828def4542",
      "productName": "Kabinväska 54 cm, 65 cm, 76 cm 4 hjul",
      "categoryId": "68b2f7a465a5cb13315a52bb"
    },
    {
      "productId": "68be85ad094d08828def4543",
      "productName": "Set med resväskor, S/M/L",
      "categoryId": "68b2f7a465a5cb13315a52bb"
    },
    {
      "productId": "68be85ad094d08828def4544",
      "productName": "Set med resväskor / Trolleyset 3 delar S/M/L",
      "categoryId": "68b2f7a465a5cb13315a52bb"
    },
    {
      "productId": "68be85ad094d08828def4545",
      "productName": "Core Light Padded Jacket M",
      "categoryId": "68b2f79d65a5cb13315a529a"
    },
    {
      "productId": "68be85ad094d08828def4546",
      "productName": "Rush 2.0 Training Jacket M",
      "categoryId": "68b2f79d65a5cb13315a529a"
    },
    {
      "productId": "68be85ad094d08828def4547",
      "productName": "Adv Unify Hybrid Jacket W",
      "categoryId": "68b2f79d65a5cb13315a529a"
    },
    {
      "productId": "68be85ad094d08828def4548",
      "productName": "Evolve Down Jacket M",
      "categoryId": "68b2f79d65a5cb13315a529a"
    },
    {
      "productId": "68be85ad094d08828def4549",
      "productName": "Squad Go Jacket M",
      "categoryId": "68b2f79d65a5cb13315a529a"
    },
    {
      "productId": "68be85ad094d08828def454a",
      "productName": "Evolve 2.0 Full Zip Jacket M",
      "categoryId": "68b2f79d65a5cb13315a529a"
    },
    {
      "productId": "68be85ad094d08828def454b",
      "productName": "Craft Träningsjacka Progress Herr",
      "categoryId": "68b2f79d65a5cb13315a529a"
    },
    {
      "productId": "68be85ad094d08828def454c",
      "productName": "Adv Explore Power Fleece Hood Jkt M",
      "categoryId": "68b2f79d65a5cb13315a529a"
    },
    {
      "productId": "68be85ad094d08828def454d",
      "productName": "Evolve Down Jacket W",
      "categoryId": "68b2f79d65a5cb13315a529a"
    },
    {
      "productId": "68be85ad094d08828def454e",
      "productName": "Core Light Padded Jacket W",
      "categoryId": "68b2f79d65a5cb13315a529a"
    },
    {
      "productId": "68be85ad094d08828def454f",
      "productName": "Core Explore Shell Jacket M",
      "categoryId": "68b2f79d65a5cb13315a529a"
    },
    {
      "productId": "68be85ad094d08828def4550",
      "productName": "Squad 2.0 Full Zip M",
      "categoryId": "68b2f79d65a5cb13315a529a"
    },
    {
      "productId": "68be85ad094d08828def4551",
      "productName": "Core Unify Wind Jacket M",
      "categoryId": "68b2f79d65a5cb13315a529a"
    },
    {
      "productId": "68be85ad094d08828def4552",
      "productName": "Squad 2.0 Full Zip W",
      "categoryId": "68b2f79d65a5cb13315a529a"
    },
    {
      "productId": "68be85ad094d08828def4553",
      "productName": "Evolve Down Jacket Jr",
      "categoryId": "68b2f79d65a5cb13315a529a"
    },
    {
      "productId": "68be85ad094d08828def4554",
      "productName": "Core Explore Lt. Insulation Jkt M",
      "categoryId": "68b2f79d65a5cb13315a529a"
    },
    {
      "productId": "68be85ad094d08828def4555",
      "productName": "Squad Go Jacket W",
      "categoryId": "68b2f79d65a5cb13315a529a"
    },
    {
      "productId": "68be85ad094d08828def4556",
      "productName": "Basic Backpack",
      "categoryId": "68b2f7a465a5cb13315a52bb"
    },
    {
      "productId": "68be85ad094d08828def4557",
      "productName": "Evolve 2.0 Full Zip Jacket Jr",
      "categoryId": "68b2f79d65a5cb13315a529a"
    },
    {
      "productId": "68be85ad094d08828def4558",
      "productName": "Core Explore Fleece Midlayer M",
      "categoryId": "68b2f79d65a5cb13315a529a"
    },
    {
      "productId": "68be85ad094d08828def4559",
      "productName": "Adv Explore Lt. Down Jkt M",
      "categoryId": "68b2f79d65a5cb13315a529a"
    },
    {
      "productId": "68be85ad094d08828def455a",
      "productName": "Adv Explore Shell Jacket M",
      "categoryId": "68b2f79d65a5cb13315a529a"
    },
    {
      "productId": "68be85ad094d08828def455b",
      "productName": "Squad Go Jacket Jr",
      "categoryId": "68b2f79d65a5cb13315a529a"
    },
    {
      "productId": "68be85ad094d08828def455c",
      "productName": "Rush 2.0 Training Jacket Jr",
      "categoryId": "68b2f79d65a5cb13315a529a"
    },
    {
      "productId": "68be85ad094d08828def455d",
      "productName": "Adv Explore Lightweight Jacket M",
      "categoryId": "68b2f79d65a5cb13315a529a"
    },
    {
      "productId": "68be85ad094d08828def455e",
      "productName": "Basic Bag",
      "categoryId": "68b2f7a465a5cb13315a52bb"
    },
    {
      "productId": "68be85ad094d08828def455f",
      "productName": "Smart Backpack",
      "categoryId": "68b2f7a465a5cb13315a52bb"
    },
    {
      "productId": "68be85ad094d08828def4560",
      "productName": "Sportbag",
      "categoryId": "68b2f7a465a5cb13315a52bb"
    },
    {
      "productId": "68be85ad094d08828def4561",
      "productName": "Backpack II",
      "categoryId": "68b2f7a465a5cb13315a52bb"
    },
    {
      "productId": "68be85ad094d08828def4562",
      "productName": "Core Explore Fleece Midlayer W",
      "categoryId": "68b2f79d65a5cb13315a529a"
    },
    {
      "productId": "68be85ad094d08828def4563",
      "productName": "Evolve Rain Jacket W",
      "categoryId": "68b2f79d65a5cb13315a529a"
    },
    {
      "productId": "68be85ad094d08828def4564",
      "productName": "Adv Explore Lt. Down Jkt W",
      "categoryId": "68b2f79d65a5cb13315a529a"
    },
    {
      "productId": "68be85ad094d08828def4565",
      "productName": "Craft Regnjacka Herr",
      "categoryId": "68b2f79d65a5cb13315a529a"
    },
    {
      "productId": "68be85ad094d08828def4566",
      "productName": "Core Explore Lt. Insulation Jkt W",
      "categoryId": "68b2f79d65a5cb13315a529a"
    },
    {
      "productId": "68be85ad094d08828def4567",
      "productName": "Adv Nordic Ski Club Jacket Jr",
      "categoryId": "68b2f79d65a5cb13315a529a"
    },
    {
      "productId": "68be85ad094d08828def4568",
      "productName": "Rush 2.0 Training Jacket W",
      "categoryId": "68b2f79d65a5cb13315a529a"
    },
    {
      "productId": "68be85ad094d08828def4569",
      "productName": "Core Explore Shell Jacket W",
      "categoryId": "68b2f79d65a5cb13315a529a"
    },
    {
      "productId": "68be85ad094d08828def456a",
      "productName": "Evolve 2.0 Full Zip Jacket W",
      "categoryId": "68b2f79d65a5cb13315a529a"
    },
    {
      "productId": "68be85ad094d08828def456b",
      "productName": "2-in-1 bag 42L",
      "categoryId": "68b2f7a465a5cb13315a52bb"
    },
    {
      "productId": "68be85ad094d08828def456c",
      "productName": "Adv Explore Power Fleece Hood Jkt W",
      "categoryId": "68b2f79d65a5cb13315a529a"
    },
    {
      "productId": "68be85ad094d08828def456d",
      "productName": "Adv Join Fz Jacket M",
      "categoryId": "68b2f79d65a5cb13315a529a"
    },
    {
      "productId": "68be85ad094d08828def456e",
      "productName": "2-in-1 bag 75L",
      "categoryId": "68b2f7a465a5cb13315a52bb"
    },
    {
      "productId": "68be85ad094d08828def456f",
      "productName": "Adv Explore Light Midlayer M",
      "categoryId": "68b2f79d65a5cb13315a529a"
    },
    {
      "productId": "68be85ad094d08828def4570",
      "productName": "Craft Målvaktströja Squad Dam",
      "categoryId": "68b2f79d65a5cb13315a529a"
    },
    {
      "productId": "68be85ad094d08828def4571",
      "productName": "Progress Ls Basket Jersey Jr",
      "categoryId": "68b2f79d65a5cb13315a529a"
    },
    {
      "productId": "68be85ad094d08828def4572",
      "productName": "Adv Explore Light Midlayer W",
      "categoryId": "68b2f79d65a5cb13315a529a"
    },
    {
      "productId": "68be85ad094d08828def4573",
      "productName": "Adv Unify Hybrid Jacket M",
      "categoryId": "68b2f79d65a5cb13315a529a"
    },
    {
      "productId": "68be85ad094d08828def4574",
      "productName": "Evolve 2.0 Half Zip Jacket M",
      "categoryId": "68b2f79d65a5cb13315a529a"
    },
    {
      "productId": "68be85ad094d08828def4575",
      "productName": "Adv Unify Hybrid Jacket W",
      "categoryId": "68b2f79d65a5cb13315a529a"
    },
    {
      "productId": "68be85ad094d08828def4578",
      "productName": "Adv Join Fz Hoodie M",
      "categoryId": "68b2f79d65a5cb13315a529a"
    },
    {
      "productId": "68be85ad094d08828def457a",
      "productName": "Adv Nordic Ski Club Jersey Jr",
      "categoryId": "68b2f79d65a5cb13315a529a"
    },
    {
      "productId": "68be85ad094d08828def457b",
      "productName": "Adv Nordic Ski Club Jersey M",
      "categoryId": "68b2f79d65a5cb13315a529a"
    },
    {
      "productId": "68be85ad094d08828def457c",
      "productName": "Squad 2.0 Full Zip Jr",
      "categoryId": "68b2f79d65a5cb13315a529a"
    },
    {
      "productId": "68be85ad094d08828def457d",
      "productName": "Squad 2.0 Full Zip W",
      "categoryId": "68b2f79d65a5cb13315a529a"
    },
    {
      "productId": "68be85ad094d08828def457e",
      "productName": "Adv Join Fz Hoodie W",
      "categoryId": "68b2f79d65a5cb13315a529a"
    },
    {
      "productId": "68be85ad094d08828def457f",
      "productName": "Progress 2.0 Gk Ls Jersey M",
      "categoryId": "68b2f79d65a5cb13315a529a"
    },
    {
      "productId": "68be85ad094d08828def4581",
      "productName": "Adv Join Hoodie M",
      "categoryId": "68b2f79d65a5cb13315a529a"
    },
    {
      "productId": "68be85ad094d08828def4583",
      "productName": "Squad 2.0 Half Zip Jr",
      "categoryId": "68b2f79d65a5cb13315a529a"
    },
    {
      "productId": "68be85ad094d08828def4584",
      "productName": "Squad 2.0 Half Zip M",
      "categoryId": "68b2f79d65a5cb13315a529a"
    },
    {
      "productId": "68be85ad094d08828def4585",
      "productName": "Progress 2.0 Gk Ls Jersey W",
      "categoryId": "68b2f79d65a5cb13315a529a"
    },
    {
      "productId": "68be85ad094d08828def4588",
      "productName": "Squad 2.0 Crewneck Jr",
      "categoryId": "68b2f79d65a5cb13315a529a"
    },
    {
      "productId": "68be85ad094d08828def4589",
      "productName": "Squad 2.0 Crewneck M",
      "categoryId": "68b2f79d65a5cb13315a529a"
    },
    {
      "productId": "68be85ad094d08828def458a",
      "productName": "Adv Join Rn Sweatshirt M",
      "categoryId": "68b2f79d65a5cb13315a529a"
    },
    {
      "productId": "68be85ad094d08828def458b",
      "productName": "Adv Join Long Hoodie W",
      "categoryId": "68b2f79d65a5cb13315a529a"
    },
    {
      "productId": "68be85ad094d08828def458c",
      "productName": "Squad 2.0 Half Zip W",
      "categoryId": "68b2f79d65a5cb13315a529a"
    },
    {
      "productId": "68be85ad094d08828def458d",
      "productName": "Squad 2.0 Crewneck W",
      "categoryId": "68b2f79d65a5cb13315a529a"
    },
    {
      "productId": "68be85ad094d08828def458e",
      "productName": "Adv Join Rn Sweatshirt W",
      "categoryId": "68b2f79d65a5cb13315a529a"
    },
    {
      "productId": "68be85ad094d08828def4590",
      "productName": "RAFAEL. Fluorescerande slap-wrap",
      "categoryId": "68b2f7a065a5cb13315a52a7"
    },
    {
      "productId": "68be85ad094d08828def4592",
      "productName": "CAMDEN. Väska i bomull (50%), återvunnen bomull (30%) och polyester (20% rPET) (280 g/ m²)",
      "categoryId": "68b2f7a465a5cb13315a52bb"
    },
    {
      "productId": "68be85ad094d08828def4593",
      "productName": "GIBRALTAR. Återvunnen presentväska av bomull (70%), polyester (30% rPET) (140 g/m²)",
      "categoryId": "68b2f7a465a5cb13315a52bb"
    },
    {
      "productId": "68be85ad094d08828def4594",
      "productName": "THC MONACO WOMEN. Dam piketröja",
      "categoryId": "68b2f79d65a5cb13315a529a"
    },
    {
      "productId": "68be85ad094d08828def4596",
      "productName": "OWENS. Set med keramikmuggar 280 ml",
      "categoryId": "68b2f7a165a5cb13315a52ae"
    },
    {
      "productId": "68be85ad094d08828def4597",
      "productName": "75089. Lanyard Tube Long Set II. Standard modeller",
      "categoryId": "68b2f79f65a5cb13315a52a5"
    },
    {
      "productId": "68be85ad094d08828def4598",
      "productName": "THC BERLIN WOMEN. Dam piketröja",
      "categoryId": "68b2f79d65a5cb13315a529a"
    },
    {
      "productId": "68be85ad094d08828def4599",
      "productName": "CHILKA. Barnkeps i polyester",
      "categoryId": "68b2f7a065a5cb13315a52a7"
    },
    {
      "productId": "68be85ad094d08828def459c",
      "productName": "CARL. återvunnen polyester (100% rPET) unisex mössa",
      "categoryId": "68b2f7a065a5cb13315a52a7"
    },
    {
      "productId": "68be85ad094d08828def459e",
      "productName": "PYRUS. Lunchlåda. 1000ml PP hermetisk låda",
      "categoryId": "68b2f79f65a5cb13315a52a5"
    },
    {
      "productId": "68be85ad094d08828def459f",
      "productName": "PHELPS. Rostfritt stål och PP mugg 470 mL",
      "categoryId": "68b2f7a165a5cb13315a52ae"
    },
    {
      "productId": "68be85ad094d08828def45a1",
      "productName": "Lanyard Tube Long Set I. Standard modeller",
      "categoryId": "68b2f79f65a5cb13315a52a5"
    },
    {
      "productId": "68be85ad094d08828def45a2",
      "productName": "Lanyard Tube Short Set. Standard modeller",
      "categoryId": "68b2f79f65a5cb13315a52a5"
    },
    {
      "productId": "68be85ad094d08828def45a4",
      "productName": "Lanyard Tube Long Set II. Standard modeller",
      "categoryId": "68b2f79f65a5cb13315a52a5"
    },
    {
      "productId": "68be85ad094d08828def45a6",
      "productName": "HAWK. återvunnen polyester (100% rPET) unisex mössa",
      "categoryId": "68b2f7a065a5cb13315a52a7"
    },
    {
      "productId": "68be85ad094d08828def45a7",
      "productName": "THC PIXEL 3XL. Kroppsvärmare med flera fickor",
      "categoryId": "68b2f79d65a5cb13315a529a"
    },
    {
      "productId": "68be85ad094d08828def45a9",
      "productName": "Community 2.0 Logo Fz Hoodie W",
      "categoryId": "68b2f79d65a5cb13315a529a"
    },
    {
      "productId": "68be85ad094d08828def45aa",
      "productName": "Community 2.0 Logo Hoodie M",
      "categoryId": "68b2f79d65a5cb13315a529a"
    },
    {
      "productId": "68be85ad094d08828def45ac",
      "productName": "Squad Go Hz M",
      "categoryId": "68b2f79d65a5cb13315a529a"
    },
    {
      "productId": "68be85ad094d08828def45ad",
      "productName": "Squad Go Hz Jr",
      "categoryId": "68b2f79d65a5cb13315a529a"
    },
    {
      "productId": "68be85ad094d08828def45ae",
      "productName": "Community 2.0 Logo Hoodie W",
      "categoryId": "68b2f79d65a5cb13315a529a"
    },
    {
      "productId": "68be85ad094d08828def45af",
      "productName": "Squad Go Hz W",
      "categoryId": "68b2f79d65a5cb13315a529a"
    }
  ],
  "productsWithMultipleSubcategories": [],
  "categorySubcategoryPairs": {},
  "timestamp": "2025-09-10T19:19:18.535Z"
}